pyisotools/__init__.py
pyisotools/__main__.py
pyisotools/apploader.py
pyisotools/bi2.py
pyisotools/bnrparser.py
pyisotools/boot.py
pyisotools/fst.py
pyisotools/iohelper.py
pyisotools/iso.py
pyisotools/gui/__init__.py
pyisotools/gui/connector.py
pyisotools/gui/customwidgets.py
pyisotools/gui/flagthread.py
pyisotools/gui/icons_rc.py
pyisotools/gui/mainwindow.py
pyisotools/gui/nodewindow.py
pyisotools/gui/settingswindow.py
pyisotools/gui/updater.py
pyisotools/gui/updatewindow.py
pyisotools/gui/workers.py
pyisotools/gui/workpathing.py
pyisotools-2.4.7.dist-info/LICENSE
pyisotools-2.4.7.dist-info/METADATA
pyisotools-2.4.7.dist-info/WHEEL
pyisotools-2.4.7.dist-info/top_level.txt
pyisotools-2.4.7.dist-info/RECORD
