Metadata-Version: 2.2
Name: pyisotools
Version: 2.4.7
Summary: Simple python library for extracting and rebuilding ISOs
Home-page: https://github.com/JoshuaMKW/pyisotools
Author: JoshuaMK
Author-email: joshuamkw2002@gmail.com
License: GNU General Public License v3.0
Classifier: Development Status :: 4 - Beta
Classifier: Intended Audience :: Developers
Classifier: Programming Language :: Python :: 3.8
Classifier: License :: OSI Approved :: GNU General Public License v3 (GPLv3)
Classifier: Operating System :: OS Independent
Requires-Python: >=3.8
License-File: LICENSE
Requires-Dist: bs4
Requires-Dist: chardet
Requires-Dist: dolreader
Requires-Dist: qdarkstyle
Requires-Dist: sortedcontainers
Requires-Dist: pillow
Requires-Dist: pygithub
Requires-Dist: PySide6
Requires-Dist: pyinstaller
Requires-Dist: pylint
Requires-Dist: setuptools
Dynamic: author
Dynamic: author-email
Dynamic: classifier
Dynamic: description
Dynamic: description-content-type
Dynamic: home-page
Dynamic: license
Dynamic: requires-dist
Dynamic: requires-python
Dynamic: summary
